ok8deploy/__init__.py
ok8deploy/ok8deploy.py
ok8deploy/config/AppConfig.py
ok8deploy/config/BaseConfig.py
ok8deploy/config/Config.py
ok8deploy/config/ConfigMap.py
ok8deploy/config/DeploymentActionConfig.py
ok8deploy/config/YmlConfig.py
ok8deploy/config/__init__.py
ok8deploy/deploy/AppDeploy.py
ok8deploy/deploy/DeploymentBundle.py
ok8deploy/deploy/OcObjectDeployer.py
ok8deploy/deploy/__init__.py
ok8deploy/k8/__init__.py
ok8deploy/oc/Model.py
ok8deploy/oc/Oc.py
ok8deploy/oc/__init__.py
ok8deploy/processing/DataPreProcessor.py
ok8deploy/processing/OcObjectMerge.py
ok8deploy/processing/ValueLoader.py
ok8deploy/processing/YmlTemplateProcessor.py
ok8deploy/processing/__init__.py
ok8deploy/utils/Cert.py
ok8deploy/utils/DictUtils.py
ok8deploy/utils/Errors.py
ok8deploy/utils/Log.py
ok8deploy/utils/__init__.py
tests/AppDeploymentTest.py
tests/DictUtilsTest.py
tests/OcObjectMergeTest.py
tests/YmlTempalteProcessorTest.py
tests/__init__.py
ok8deploy-1.0.4.dist-info/LICENSE
ok8deploy-1.0.4.dist-info/METADATA
ok8deploy-1.0.4.dist-info/WHEEL
ok8deploy-1.0.4.dist-info/entry_points.txt
ok8deploy-1.0.4.dist-info/top_level.txt
ok8deploy-1.0.4.dist-info/RECORD
