Metadata-Version: 2.1
Name: ok8deploy
Version: 1.0.4
Summary: Simple Openshift / K8 template engine with state tracking
Home-page: https://github.com/davidgiga1993/OpenK8Deploy
Author: davidgiga1993
Author-email: david@dev-core.org
License: UNKNOWN
Platform: UNKNOWN
Classifier: Development Status :: 4 - Beta
Classifier: Programming Language :: Python :: 3
Classifier: License :: OSI Approved :: MIT License
Classifier: Operating System :: OS Independent
Classifier: Topic :: Software Development :: Libraries
